djangomon/__init__.py
djangomon/middleware.py
djangomon-0.2.0.dist-info/METADATA
djangomon-0.2.0.dist-info/WHEEL
djangomon-0.2.0.dist-info/RECORD
