Metadata-Version: 2.1
Name: djangomon
Version: 0.2.0
Summary: CPU and RAM monitor for django request response cycle
License: MIT
Author: Dhrumil Mistry
Author-email: 56185972+dmdhrumilmistry@users.noreply.github.com
Requires-Python: >=3.7,<4.0
Classifier: License :: OSI Approved :: MIT License
Classifier: Programming Language :: Python :: 3
Classifier: Programming Language :: Python :: 3.7
Classifier: Programming Language :: Python :: 3.8
Classifier: Programming Language :: Python :: 3.9
Classifier: Programming Language :: Python :: 3.10
Classifier: Programming Language :: Python :: 3.11
Requires-Dist: psutil (>=5.9.5,<6.0.0)
